sqlalchemy_json/__init__.py
sqlalchemy_json/track.py
sqlalchemy_json-0.7.0.dist-info/LICENSE
sqlalchemy_json-0.7.0.dist-info/METADATA
sqlalchemy_json-0.7.0.dist-info/WHEEL
sqlalchemy_json-0.7.0.dist-info/top_level.txt
sqlalchemy_json-0.7.0.dist-info/RECORD
