Metadata-Version: 2.1
Name: sqlalchemy-json
Version: 0.7.0
Summary: JSON type with nested change tracking for SQLAlchemy
Home-page: https://github.com/edelooff/sqlalchemy-json
Author: Elmer de Looff
Author-email: elmer.delooff@gmail.com
License: BSD
Keywords: sqlalchemy json mutable
Classifier: Development Status :: 4 - Beta
Classifier: Intended Audience :: Developers
Classifier: License :: OSI Approved :: BSD License
Classifier: Programming Language :: Python
Classifier: Programming Language :: Python :: 3
Classifier: Topic :: Database
Requires-Python: >= 3.6
Provides-Extra: dev
License-File: LICENSE
